{
    "click": {
        "name": "click",
        "phrase": [
            "кликни",
            "сделай клик"
        ],
        "paramType": {
            "xy": "(int, int)",
            "double_click": "boolean"
        },
        "returnType": {
            "xy": "(int, int)"
        },
        "code": "\nimport pyautogui\n\ndef click(data):\n    try:\n        if 'xy' in data:\n            x, y = data['xy']\n        else:\n            x, y = pyautogui.position()\n            data['xy'] = x, y\n        if pyautogui.onScreen(x, y):\n            if data.get('double_click', False):\n                print(\"Выполняю двойной клик мышкой в\", x, y)\n                pyautogui.doubleClick(x, y)\n                del data['doubleClick']\n            else:\n                print(\"Выполняю клик мышкой в\", x, y)\n                pyautogui.click(x, y)\n        else:\n            data['error'] = \"Эти координаты находятся вне вашего экрана\", *pyautogui.size()\n    except Exception as e:\n        data['error'] = str(e)\n    return data\n\nclick(data)"
    }
}